{
    "name": "RUN N' CHOMP D-luxe",
    "version": "0.0.1",
    "description": "",
    "dependencies": {
        "device": "*"
    },
    "files": [
        "main.blocks",
        "main.ts",
        "README.md",
        "assets.json",
        "tilemap.g.jres",
        "tilemap.g.ts",
        "images.g.jres",
        "images.g.ts",
        "pxt.json",
        ".simstate.json"
    ],
    "testFiles": [
        "test.ts"
    ],
    "targetVersions": {
        "target": "1.12.53",
        "targetId": "arcade"
    },
    "supportedTargets": [
        "arcade"
    ],
    "preferredEditor": "blocksprj"
}
